azappinsights_logger/__init__.py
azappinsights_logger/custom_log_processor.py
azappinsights_logger/logger.py
azappinsights_logger-0.0.8.dist-info/licenses/LICENSE
azappinsights_logger-0.0.8.dist-info/METADATA
azappinsights_logger-0.0.8.dist-info/WHEEL
azappinsights_logger-0.0.8.dist-info/top_level.txt
azappinsights_logger-0.0.8.dist-info/RECORD
