Metadata-Version: 2.4
Name: azappinsights-logger
Version: 0.0.8
Summary: A simple logging utility for sending logs to azure application insights using AzureLogHandler
Author-email: Ranti Familusi <ranti.familusi@ibm.com>
Project-URL: Homepage, https://dev.azure.com/IBM-CA-MSPRACTICE/Maximo-Copilot/_git/utilities/az-app-insight-logger
Project-URL: Bug Tracker, https://dev.azure.com/IBM-CA-MSPRACTICE/Maximo-Copilot/_workitems/edit/146
Classifier: Programming Language :: Python :: 3
Classifier: License :: OSI Approved :: MIT License
Classifier: Operating System :: OS Independent
Requires-Python: >=3.7
License-File: LICENSE
Requires-Dist: python-dotenv
Requires-Dist: azure-monitor-opentelemetry
Requires-Dist: opentelemetry-sdk
Dynamic: license-file
